getl/__init__.py
getl/block.py
getl/blocks/__init__.py
getl/blocks/custom/__init__.py
getl/blocks/custom/entrypoint.py
getl/blocks/load/__init__.py
getl/blocks/load/entrypoint.py
getl/blocks/transform/__init__.py
getl/blocks/transform/add_column/__init__.py
getl/blocks/transform/add_column/date.py
getl/blocks/transform/entrypoint.py
getl/blocks/transform/transform.py
getl/blocks/write/__init__.py
getl/blocks/write/batch_delta.py
getl/blocks/write/entrypoint.py
getl/common/__init__.py
getl/common/delta_table.py
getl/common/errors.py
getl/common/hive_table.py
getl/common/s3path.py
getl/common/type_checker.py
getl/common/upsert.py
getl/common/utils.py
getl/fileregistry/__init__.py
getl/fileregistry/base.py
getl/fileregistry/delta_diff.py
getl/fileregistry/entrypoint.py
getl/fileregistry/fileregistry_utils.py
getl/fileregistry/s3_date_prefix_scan.py
getl/fileregistry/s3_full_scan.py
getl/lift.py
getl/lift_definition.py
getl/logging.py
getl/manager.py
husqvarna_getl-3.4.0.dist-info/LICENSE.md
husqvarna_getl-3.4.0.dist-info/METADATA
husqvarna_getl-3.4.0.dist-info/WHEEL
husqvarna_getl-3.4.0.dist-info/entry_points.txt
husqvarna_getl-3.4.0.dist-info/RECORD
