Metadata-Version: 2.1
Name: husqvarna-getl
Version: 3.4.0
Summary: An elegant way to ETL'ing
Home-page: https://github.com/husqvarnagroup/GETL/
License: MIT
Author: Linus Wallin
Author-email: linus.wallin@husqvarnagroup.com
Requires-Python: >=3.8,<4.0
Classifier: Development Status :: 3 - Alpha
Classifier: License :: OSI Approved :: MIT License
Classifier: Programming Language :: Python
Classifier: Programming Language :: Python :: 3
Classifier: Programming Language :: Python :: 3.8
Classifier: Programming Language :: Python :: 3.9
Classifier: Programming Language :: Python :: 3.10
Classifier: Programming Language :: Python :: 3.11
Classifier: Programming Language :: Python :: 3.12
Requires-Dist: boto3
Requires-Dist: mysql-connector-python
Requires-Dist: oyaml
Requires-Dist: psycopg2-binary
Requires-Dist: pyspark (>=3.2,<3.6)
Requires-Dist: typeguard
Project-URL: Documentation, https://getl.readthedocs.io/
Project-URL: Repository, https://github.com/husqvarnagroup/GETL/
